README.txt
setup.cfg
setup.py
repoze/__init__.py
repoze.who.plugins.beaker_tkt.egg-info/PKG-INFO
repoze.who.plugins.beaker_tkt.egg-info/SOURCES.txt
repoze.who.plugins.beaker_tkt.egg-info/dependency_links.txt
repoze.who.plugins.beaker_tkt.egg-info/not-zip-safe
repoze.who.plugins.beaker_tkt.egg-info/requires.txt
repoze.who.plugins.beaker_tkt.egg-info/top_level.txt
repoze/who/__init__.py
repoze/who/plugins/__init__.py
repoze/who/plugins/beaker_tkt.py
repoze/who/plugins/test_beaker.py