Metadata-Version: 1.0
Name: repoze.who.plugins.beaker_tkt
Version: 0.1
Summary: Identifier (auth_tkt) plugin with beaker.session cache implementation
Home-page: http://www.fubar.si
Author: Domen Kozar
Author-email: domen@dev.si
License: /
Keywords: beaker session auth tkt repoze.who
Platform: UNKNOWN
